select.py
setup.py
micropython_select.egg-info/PKG-INFO
micropython_select.egg-info/SOURCES.txt
micropython_select.egg-info/dependency_links.txt
micropython_select.egg-info/requires.txt
micropython_select.egg-info/top_level.txt