Metadata-Version: 1.0
Name: micropython-select
Version: 0.1.2
Summary: select module for MicroPython
Home-page: https://github.com/micropython/micropython/issues/405
Author: MicroPython Developers
Author-email: micro-python@googlegroups.com
License: MIT
Platform: UNKNOWN
